fluxura/__init__.py
fluxura/fluxura.py
fluxura-0.1.1a2.dist-info/licenses/LICENSE
fluxura-0.1.1a2.dist-info/METADATA
fluxura-0.1.1a2.dist-info/WHEEL
fluxura-0.1.1a2.dist-info/top_level.txt
fluxura-0.1.1a2.dist-info/RECORD
