Metadata-Version: 2.4
Name: fluxura
Version: 0.1.1a2
Summary: A soon-to-be easy way to style outputs in terminal
Author-email: Vivaan Sinha <vivaan.sinha2010.creation@gmail.com>
Project-URL: Homepage, https://github.com/VDV1llain/fluxura
Project-URL: Issues, https://github.com/VDV1llain/fluxura/issues
Classifier: Programming Language :: Python :: 3
Classifier: License :: OSI Approved :: MIT License
Classifier: Operating System :: OS Independent
Classifier: Development Status :: 3 - Alpha
Requires-Python: >=3.6
License-File: LICENSE
Dynamic: license-file
